llm_memory_sdk/core/__init__.py
llm_memory_sdk/core/convention.py
llm_memory_sdk/core/entities.py
llm_memory_sdk/core/implementation.py
llm_memory_sdk/core/prompt.py
llm_memory_sdk/core/structured.py
llm_memory_sdk-0.0.2.dist-info/METADATA
llm_memory_sdk-0.0.2.dist-info/WHEEL
llm_memory_sdk-0.0.2.dist-info/top_level.txt
llm_memory_sdk-0.0.2.dist-info/RECORD
