Metadata-Version: 2.4
Name: llm-memory-sdk
Version: 0.0.2
Summary: Currently for internal use only.
Author-email: Stream <Stream_2@qq.com>
Requires-Python: >=3.11
Requires-Dist: pydantic>=2.11.7
Requires-Dist: setuptools>=80.0
